{"type":"FeatureCollection","features":[{"type":"Feature","id":1,"geometry":{"type":"Point","coordinates":[-80.52148930799996,43.45960271000001],"bbox":[-80.52148930799996,43.45960271000001,-80.52148930799996,43.45960271000001]},"properties":{"OBJECTID":1,"TITLE":"John Labatt Barley field","ARTIST":"Jane Buyers","INSTALLED":"2001","MATERIAL":"Steel and copper","LOCATION":"Labatt Parkette - Park Street at Norman - small parkette near Catalina Homes","TOUR_AREA":"Other","OWNER":"COW","STATUS":"installed","URL":"http://www.waterloo.ca/uploads/634870636631205963_Final.jpg","LONGITUDE":"-80.5214893083141","LATITUDE":"43.4596027104015","CreationDate":"2015-09-23T13:50:37.762Z","Creator":"OpenData_Waterloo","EditDate":"2015-09-23T13:50:37.762Z","Editor":"OpenData_Waterloo"}},{"type":"Feature","id":2,"geometry":{"type":"Point","coordinates":[-80.52446783099998,43.465739669000016],"bbox":[-80.52446783099998,43.465739669000016,-80.52446783099998,43.465739669000016]},"properties":{"OBJECTID":2,"TITLE":"Looking Outward And Inward","ARTIST":"Susan Low-Beer","INSTALLED":"1995 est","MATERIAL":"Steel and ceramic clay","LOCATION":"Waterloo Public Library – (Dupont St side) Dupont & Albert","TOUR_AREA":"Uptown","OWNER":"COW","STATUS":"installed","URL":"http://www.waterloo.ca/uploads/634870640407348596_Final.jpg","LONGITUDE":"-80.5244678309922","LATITUDE":"43.4657396687924","CreationDate":"2015-09-23T13:50:37.762Z","Creator":"OpenData_Waterloo","EditDate":"2015-09-23T13:50:37.762Z","Editor":"OpenData_Waterloo"}},{"type":"Feature","id":3,"geometry":{"type":"Point","coordinates":[-80.50185101099999,43.518895447000006],"bbox":[-80.50185101099999,43.518895447000006,-80.50185101099999,43.518895447000006]},"properties":{"OBJECTID":3,"TITLE":"Vessel","ARTIST":"Stephen Cruise","INSTALLED":"2003","MATERIAL":"Granite","LOCATION":"RIM Park - Sportsplex Entrance","TOUR_AREA":"RIM Park","OWNER":"COW","STATUS":"installed","URL":"http://www.waterloo.ca/uploads/634870649791857079_Final.jpg","LONGITUDE":"-80.5018510111207","LATITUDE":"43.5188954470683","CreationDate":"2015-09-23T13:50:37.762Z","Creator":"OpenData_Waterloo","EditDate":"2015-09-23T13:50:37.762Z","Editor":"OpenData_Waterloo"}},{"type":"Feature","id":4,"geometry":{"type":"Point","coordinates":[-80.52184661299998,43.463953395000004],"bbox":[-80.52184661299998,43.463953395000004,-80.52184661299998,43.463953395000004]},"properties":{"OBJECTID":4,"TITLE":"Triad: Dual, Interface And Reunited","ARTIST":"Ann Roberts","INSTALLED":"1981","MATERIAL":"Bronze","LOCATION":"Uptown Parkade - Entrance on King St (3 objects) near Willis Way","TOUR_AREA":"Uptown","OWNER":"COW","STATUS":"installed","URL":"http://www.waterloo.ca/uploads/634870649268164159_Final.jpg","LONGITUDE":"-80.5218466128449","LATITUDE":"43.4639533948397","CreationDate":"2015-09-23T13:50:37.762Z","Creator":"OpenData_Waterloo","EditDate":"2015-09-23T13:50:37.762Z","Editor":"OpenData_Waterloo"}},{"type":"Feature","id":5,"geometry":{"type":"Point","coordinates":[-80.53262414799997,43.464394992000024],"bbox":[-80.53262414799997,43.464394992000024,-80.53262414799997,43.464394992000024]},"properties":{"OBJECTID":5,"TITLE":"Etched Into Memory","ARTIST":"Evan Penney & Stephen Andrews","INSTALLED":"1992","MATERIAL":"Fibreglass with a stone finish and brass plates","LOCATION":"Waterloo Memorial Recreation Complex - indoors, near the arena steps\r\n101 Father David Bauer Drive\r\n","TOUR_AREA":"Uptown","OWNER":"COW","STATUS":"installed","URL":"http://www.waterloo.ca/uploads/634870634517090250_Final.jpg","LONGITUDE":"-80.5326241478785","LATITUDE":"43.4643949922217","CreationDate":"2015-09-23T13:50:37.762Z","Creator":"OpenData_Waterloo","EditDate":"2015-09-23T13:50:37.762Z","Editor":"OpenData_Waterloo"}},{"type":"Feature","id":6,"geometry":{"type":"Point","coordinates":[-80.49291259999995,43.516849140000005],"bbox":[-80.49291259999995,43.516849140000005,-80.49291259999995,43.516849140000005]},"properties":{"OBJECTID":6,"TITLE":"Our House","ARTIST":"Tony Urquhart","INSTALLED":"2003","MATERIAL":"Painted Steel","LOCATION":"Grey Silo Park House -  - adjacent to golf club house","TOUR_AREA":"RIM Park","OWNER":"COW","STATUS":"installed","URL":"http://www.waterloo.ca/uploads/634870642288555900_Final.jpg","LONGITUDE":"-80.4929126004458","LATITUDE":"43.5168491395063","CreationDate":"2015-09-23T13:50:37.762Z","Creator":"OpenData_Waterloo","EditDate":"2015-09-23T13:50:37.762Z","Editor":"OpenData_Waterloo"}},{"type":"Feature","id":7,"geometry":{"type":"Point","coordinates":[-80.52159538899997,43.46735809100002],"bbox":[-80.52159538899997,43.46735809100002,-80.52159538899997,43.46735809100002]},"properties":{"OBJECTID":7,"TITLE":"Aspiring Orchard","ARTIST":"Catherine Paleczny","INSTALLED":"2010","MATERIAL":"Stainless Steel","LOCATION":"36 Regina Street N at Bridgeport Rd","TOUR_AREA":"Uptown","OWNER":"COW","STATUS":"installed","URL":"http://www.waterloo.ca/uploads/634870630763723658_Final.jpg","LONGITUDE":"-80.521595389052","LATITUDE":"43.4673580906382","CreationDate":"2015-09-23T13:50:37.762Z","Creator":"OpenData_Waterloo","EditDate":"2015-09-23T13:50:37.762Z","Editor":"OpenData_Waterloo"}},{"type":"Feature","id":8,"geometry":{"type":"Point","coordinates":[-80.52773078599995,43.47542171500001],"bbox":[-80.52773078599995,43.47542171500001,-80.52773078599995,43.47542171500001]},"properties":{"OBJECTID":8,"TITLE":"Veterans Memorial","ARTIST":"Timothy Schmalz","INSTALLED":"2006","MATERIAL":"Bronze","LOCATION":"Scholars Green – University Ave & Hazel St","TOUR_AREA":"Other","OWNER":"COW","STATUS":"installed","URL":"http://www.waterloo.ca/uploads/634870650907103038_Final.jpg","LONGITUDE":"-80.5277307864402","LATITUDE":"43.4754217146466","CreationDate":"2015-09-23T13:50:37.762Z","Creator":"OpenData_Waterloo","EditDate":"2015-09-23T13:50:37.762Z","Editor":"OpenData_Waterloo"}},{"type":"Feature","id":9,"geometry":{"type":"Point","coordinates":[-80.57107843399996,43.47405951900001],"bbox":[-80.57107843399996,43.47405951900001,-80.57107843399996,43.47405951900001]},"properties":{"OBJECTID":9,"TITLE":"Origami Goose","ARTIST":"Jyhling Lee","INSTALLED":"2011-12","MATERIAL":"Powder coated aluminum","LOCATION":"Westside Library & YMCA - Fischer-Hallman & Laurelwood","TOUR_AREA":"Westside","OWNER":"COW","STATUS":"installed","URL":"http://www.waterloo.ca/uploads/634870640976125595_Final.jpg","LONGITUDE":"-80.5710784342268","LATITUDE":"43.4740595193248","CreationDate":"2015-09-23T13:50:37.762Z","Creator":"OpenData_Waterloo","EditDate":"2015-09-23T13:50:37.762Z","Editor":"OpenData_Waterloo"}},{"type":"Feature","id":10,"geometry":{"type":"Point","coordinates":[-80.52027749299998,43.463980832000004],"bbox":[-80.52027749299998,43.463980832000004,-80.52027749299998,43.463980832000004]},"properties":{"OBJECTID":10,"TITLE":"Laurel Creek","ARTIST":"Natalie McHaffie","INSTALLED":"1988","MATERIAL":"Cypress wood and stainless steel","LOCATION":"Waterloo City Centre – North side, adjacent to the creek itself","TOUR_AREA":"Uptown","OWNER":"COW","STATUS":"installed","URL":"http://www.waterloo.ca/uploads/634870637818056048_Final.jpg","LONGITUDE":"-80.5202774927101","LATITUDE":"43.4639808320805","CreationDate":"2015-09-23T13:50:37.762Z","Creator":"OpenData_Waterloo","EditDate":"2015-09-23T13:50:37.762Z","Editor":"OpenData_Waterloo"}},{"type":"Feature","id":11,"geometry":{"type":"Point","coordinates":[-80.49435983499995,43.51761886800003],"bbox":[-80.49435983499995,43.51761886800003,-80.49435983499995,43.51761886800003]},"properties":{"OBJECTID":11,"TITLE":"Golden Queen Hybrid","ARTIST":"Jane Buyers","INSTALLED":"2004","MATERIAL":"Bronze","LOCATION":"RIM Park - Martin Farm (across the golf road from the ...)","TOUR_AREA":"RIM Park","OWNER":"COW","STATUS":"installed","URL":"http://www.waterloo.ca/uploads/634870635208951465_Final.jpg","LONGITUDE":"-80.4943598351191","LATITUDE":"43.517618868335","CreationDate":"2015-09-23T13:50:37.762Z","Creator":"OpenData_Waterloo","EditDate":"2015-09-23T13:50:37.762Z","Editor":"OpenData_Waterloo"}},{"type":"Feature","id":12,"geometry":{"type":"Point","coordinates":[-80.53199141799996,43.46404093700002],"bbox":[-80.53199141799996,43.46404093700002,-80.53199141799996,43.46404093700002]},"properties":{"OBJECTID":12,"TITLE":"The Human Quilt","ARTIST":"Réal Faulkenham","INSTALLED":"2000","MATERIAL":"Paint on marine quality plywood","LOCATION":"Waterloo Memorial Recreation Complex - Front Exterior Wall","TOUR_AREA":"Uptown","OWNER":"COW","STATUS":"installed","URL":"http://www.waterloo.ca/uploads/634870645673917846_Final.jpg","LONGITUDE":"-80.5319914181346","LATITUDE":"43.4640409369816","CreationDate":"2015-09-23T13:50:37.762Z","Creator":"OpenData_Waterloo","EditDate":"2015-09-23T13:50:37.762Z","Editor":"OpenData_Waterloo"}},{"type":"Feature","id":13,"geometry":{"type":"Point","coordinates":[-80.50362446599996,43.51854055700002],"bbox":[-80.50362446599996,43.51854055700002,-80.50362446599996,43.51854055700002]},"properties":{"OBJECTID":13,"TITLE":"Prayerflags","ARTIST":"John Hofstetter","INSTALLED":"200606","MATERIAL":"Steel, glass, copper, aluminum","LOCATION":"Rotary Peace Park, RIM Park, adjacent to main building","TOUR_AREA":"RIM Park","OWNER":"COW","STATUS":"installed","URL":"http://www.waterloo.ca/uploads/634870643032677207_Final.jpg","LONGITUDE":"-80.5036244659004","LATITUDE":"43.5185405569384","CreationDate":"2015-09-23T13:50:37.762Z","Creator":"OpenData_Waterloo","EditDate":"2015-09-23T13:50:37.762Z","Editor":"OpenData_Waterloo"}},{"type":"Feature","id":14,"geometry":{"type":"Point","coordinates":[-80.53025974399998,43.46530351300001],"bbox":[-80.53025974399998,43.46530351300001,-80.53025974399998,43.46530351300001]},"properties":{"OBJECTID":14,"TITLE":"Choice","ARTIST":"Ruth Abernethy","INSTALLED":"2007","MATERIAL":"Stainless Steel","LOCATION":"Father David Bauer Drive – just across the road from the WMRC entrances (4 objects)","TOUR_AREA":"Uptown","OWNER":"COW","STATUS":"installed","URL":"http://www.waterloo.ca/uploads/634870631870389601_Final.jpg","LONGITUDE":"-80.5302597442686","LATITUDE":"43.465303513115","CreationDate":"2015-09-23T13:50:37.762Z","Creator":"OpenData_Waterloo","EditDate":"2015-09-23T13:50:37.762Z","Editor":"OpenData_Waterloo"}},{"type":"Feature","id":15,"geometry":{"type":"Point","coordinates":[-80.52228649699998,43.46374498000003],"bbox":[-80.52228649699998,43.46374498000003,-80.52228649699998,43.46374498000003]},"properties":{"OBJECTID":15,"TITLE":"The Waterloo Bell - Bell for Kepler","ARTIST":"Royden Rabinowitch","INSTALLED":"2009","MATERIAL":"Corten Steel","LOCATION":"Public Square – Willis Way & King","TOUR_AREA":"Uptown","OWNER":"COW","STATUS":"installed","URL":"http://www.waterloo.ca/uploads/634870647008032189_Final.jpg","LONGITUDE":"-80.5222864969917","LATITUDE":"43.4637449802513","CreationDate":"2015-09-23T13:50:37.762Z","Creator":"OpenData_Waterloo","EditDate":"2015-09-23T13:50:37.762Z","Editor":"OpenData_Waterloo"}},{"type":"Feature","id":16,"geometry":{"type":"Point","coordinates":[-80.48838969299999,43.51497090400002],"bbox":[-80.48838969299999,43.51497090400002,-80.48838969299999,43.51497090400002]},"properties":{"OBJECTID":16,"TITLE":"Tree","ARTIST":"Paul Frenette","INSTALLED":"2009","MATERIAL":"Black Maple wood","LOCATION":"Grey Silo Golf Course (1st fairway)","TOUR_AREA":"RIM Park","OWNER":"COW","STATUS":"installed","URL":"http://www.waterloo.ca/uploads/634870647981005898_Final.jpg","LONGITUDE":"-80.4883896933277","LATITUDE":"43.5149709040592","CreationDate":"2015-09-23T13:50:37.762Z","Creator":"OpenData_Waterloo","EditDate":"2015-09-23T13:50:37.762Z","Editor":"OpenData_Waterloo"}},{"type":"Feature","id":17,"geometry":{"type":"Point","coordinates":[-80.49917120599997,43.51965224600002],"bbox":[-80.49917120599997,43.51965224600002,-80.49917120599997,43.51965224600002]},"properties":{"OBJECTID":17,"TITLE":"Rein in the Wind","ARTIST":"Carlos Basanta","INSTALLED":"2011","MATERIAL":"Stainless Steel","LOCATION":"RIM Park Premier Sports Fields - entrance feature","TOUR_AREA":"RIM Park","OWNER":"COW","STATUS":"installed","URL":"http://www.waterloo.ca/uploads/634870644225923303_Final.jpg","LONGITUDE":"-80.4991712059559","LATITUDE":"43.5196522458138","CreationDate":"2015-09-23T13:50:37.762Z","Creator":"OpenData_Waterloo","EditDate":"2015-09-23T13:50:37.762Z","Editor":"OpenData_Waterloo"}},{"type":"Feature","id":18,"geometry":{"type":"Point","coordinates":[-80.53183560999997,43.465266867000025],"bbox":[-80.53183560999997,43.465266867000025,-80.53183560999997,43.465266867000025]},"properties":{"OBJECTID":18,"TITLE":"Choice","ARTIST":"Ruth Abernethy","INSTALLED":"2007","MATERIAL":"Stainless Steel","LOCATION":"Father David Bauer Drive – just across the road from the WMRC entrances (4 objects)","TOUR_AREA":"Uptown","OWNER":"COW","STATUS":"installed","URL":"http://www.waterloo.ca/uploads/634870632585026857_Final.jpg","LONGITUDE":"-80.531835610064","LATITUDE":"43.4652668667418","CreationDate":"2015-09-23T13:50:37.762Z","Creator":"OpenData_Waterloo","EditDate":"2015-09-23T13:50:37.762Z","Editor":"OpenData_Waterloo"}},{"type":"Feature","id":19,"geometry":{"type":"Point","coordinates":[-80.53670492999998,43.46442264200002],"bbox":[-80.53670492999998,43.46442264200002,-80.53670492999998,43.46442264200002]},"properties":{"OBJECTID":19,"TITLE":"Choice","ARTIST":"Ruth Abernethy","INSTALLED":"2007","MATERIAL":"Stainless Steel","LOCATION":"Father David Bauer Drive – just across the road from the WMRC entrances (4 objects)","TOUR_AREA":"Uptown","OWNER":"COW","STATUS":"installed","URL":"http://www.waterloo.ca/uploads/634870633144287839_Final.jpg","LONGITUDE":"-80.5367049303715","LATITUDE":"43.4644226417745","CreationDate":"2015-09-23T13:50:37.762Z","Creator":"OpenData_Waterloo","EditDate":"2015-09-23T13:50:37.762Z","Editor":"OpenData_Waterloo"}},{"type":"Feature","id":20,"geometry":{"type":"Point","coordinates":[-80.53737034999995,43.46398858500001],"bbox":[-80.53737034999995,43.46398858500001,-80.53737034999995,43.46398858500001]},"properties":{"OBJECTID":20,"TITLE":"Choice","ARTIST":"Ruth Abernethy","INSTALLED":"2007","MATERIAL":"Stainless Steel","LOCATION":"Father David Bauer Drive – just across the road from the WMRC entrances (4 objects)","TOUR_AREA":"Uptown","OWNER":"COW","STATUS":"installed","URL":"http://www.waterloo.ca/uploads/634870633862513100_Final.jpg","LONGITUDE":"-80.5373703497618","LATITUDE":"43.4639885848173","CreationDate":"2015-09-23T13:50:37.762Z","Creator":"OpenData_Waterloo","EditDate":"2015-09-23T13:50:37.762Z","Editor":"OpenData_Waterloo"}},{"type":"Feature","id":21,"geometry":{"type":"Point","coordinates":[-80.49811164499994,43.51401537700002],"bbox":[-80.49811164499994,43.51401537700002,-80.49811164499994,43.51401537700002]},"properties":{"OBJECTID":21,"TITLE":"Water to Fire","ARTIST":"Ernest Daetwyler","INSTALLED":"2001-12","MATERIAL":"Wood","LOCATION":"Fire Station no 4 - University Ave E","TOUR_AREA":"RIM Park","OWNER":"COW","STATUS":"pending","URL":null,"LONGITUDE":"-80.4981116448066","LATITUDE":"43.5140153766932","CreationDate":"2015-09-23T13:50:37.762Z","Creator":"OpenData_Waterloo","EditDate":"2015-09-23T13:50:37.762Z","Editor":"OpenData_Waterloo"}},{"type":"Feature","id":22,"geometry":{"type":"Point","coordinates":[-80.52582147199996,43.46474962100001],"bbox":[-80.52582147199996,43.46474962100001,-80.52582147199996,43.46474962100001]},"properties":{"OBJECTID":22,"TITLE":"(2 sculptures - C2G2)","ARTIST":"-","INSTALLED":"-","MATERIAL":"-","LOCATION":"Canadian Clay & Glass Gallery - Caroline & Erb","TOUR_AREA":"Uptown","OWNER":"C2G2","STATUS":"installed","URL":null,"LONGITUDE":"-80.5258214723374","LATITUDE":"43.4647496209829","CreationDate":"2015-09-23T13:50:37.762Z","Creator":"OpenData_Waterloo","EditDate":"2015-09-23T13:50:37.762Z","Editor":"OpenData_Waterloo"}}],"name":"PublicArt","updated_at":1443092940000,"retrieved_at":1445519834987,"expires_at":1445606234987,"count":22}